AUTHORS.txt
LICENSE.txt
MANIFEST.in
PROJECT.txt
README.rst
setup.cfg
setup.py
insolater/.swo
insolater/.swp
insolater/__init__.py
insolater/__init__.pyc
insolater/insolater.py
insolater/insolater.pyc
insolater/run.py
insolater/run.pyc
insolater/version_tools.py
insolater/version_tools.pyc
insolater/version_tools_compressed.py
insolater/version_tools_git.py
insolater/versioncmp.py
insolater.egg-info/PKG-INFO
insolater.egg-info/SOURCES.txt
insolater.egg-info/dependency_links.txt
insolater.egg-info/entry_points.txt
insolater.egg-info/requires.txt
insolater.egg-info/top_level.txt