Metadata-Version: 1.1
Name: insolater
Version: 0.0.1
Summary: Tool to easily switch between original and modified versions of a directory.
Home-page: github.com/davidnk/insolater
Author: David Karesh
Author-email: davidnk@gmail.com
License: The MIT License (MIT)
